License.txt
README.md
setup.cfg
setup.py
Topsis_Vansh_102103072.egg-info/PKG-INFO
Topsis_Vansh_102103072.egg-info/SOURCES.txt
Topsis_Vansh_102103072.egg-info/dependency_links.txt
Topsis_Vansh_102103072.egg-info/entry_points.txt
Topsis_Vansh_102103072.egg-info/requires.txt
Topsis_Vansh_102103072.egg-info/top_level.txt
topsis/__init__.py
topsis/__main__.py