Metadata-Version: 2.1
Name: Topsis-Vansh-102103072
Version: 1.1.1
Summary: This is a library for implementing Topsis in command line
Home-page: https://github.com/Vansh-Batra10/Topsis-Vansh-102103072
Download-URL: https://github.com/Vansh-Batra10/Topsis-Vansh-102103072/archive/refs/tags/v1.1.1.tar.gz 
Author: Vansh Batra
Author-email: batravansh162@gmail.com
License: MIT
Keywords: TOPSIS,Command Line
Classifier: Development Status :: 3 - Alpha
Classifier: Intended Audience :: Developers
Classifier: Topic :: Software Development :: Build Tools
Classifier: License :: OSI Approved :: MIT License
Classifier: Programming Language :: Python :: 3
Classifier: Programming Language :: Python :: 3.4
Classifier: Programming Language :: Python :: 3.5
Classifier: Programming Language :: Python :: 3.6
Classifier: Programming Language :: Python :: 3.7
Classifier: Programming Language :: Python :: 3.8
Classifier: Programming Language :: Python :: 3.9
Classifier: Programming Language :: Python :: 3.10
Classifier: Programming Language :: Python :: 3.11
Classifier: Programming Language :: Python :: 3.12
License-File: License.txt
